myopenalgo/__init__.py
myopenalgo/orders.py
tests/__init__.py
tests/test_orders.py
myopenalgo-1.0.3.dist-info/LICENSE
myopenalgo-1.0.3.dist-info/METADATA
myopenalgo-1.0.3.dist-info/WHEEL
myopenalgo-1.0.3.dist-info/top_level.txt
myopenalgo-1.0.3.dist-info/RECORD
