Metadata-Version: 2.1
Name: myopenalgo
Version: 1.0.3
Summary: A Python library for interacting with OpenAlgo's trading APIs
Home-page: https://openalgo.in
Author: Rajandran R
Author-email: rajandran@marketcalls.in
Classifier: Programming Language :: Python :: 3
Classifier: License :: OSI Approved :: MIT License
Classifier: Operating System :: OS Independent
Requires-Python: >=3.6
License-File: LICENSE
Requires-Dist: requests
